Metadata-Version: 1.0
Name: gaussian-binomial-distributions-vbcsja
Version: 7.781
Summary: Gaussian and Binomial distributions
Home-page: UNKNOWN
Author: Maximilian
Author-email: max@something.com
License: UNKNOWN
Platform: UNKNOWN
